LICENSE
steam_tradeoffer_manager/__init__.py
steam_tradeoffer_manager/_monkey_patch.py
steam_tradeoffer_manager/base/__init__.py
steam_tradeoffer_manager/base/abc.py
steam_tradeoffer_manager/base/bot.py
steam_tradeoffer_manager/base/enums.py
steam_tradeoffer_manager/base/exceptions.py
steam_tradeoffer_manager/base/mixins.py
steam_tradeoffer_manager/base/pool.py
steam_tradeoffer_manager/bot.py
steam_tradeoffer_manager/inventory.py
steam_tradeoffer_manager/item.py
steam_tradeoffer_manager/items.py
steam_tradeoffer_manager/manager.py
steam_tradeoffer_manager/mixins.py
steam_tradeoffer_manager/offer.py
steam_tradeoffer_manager/storage.py
steam_tradeoffer_manager/trades.py
steam_tradeoffer_manager/utils.py
steam_tradeoffer_manager-0.1.2.dist-info/LICENSE
steam_tradeoffer_manager-0.1.2.dist-info/WHEEL
steam_tradeoffer_manager-0.1.2.dist-info/METADATA
steam_tradeoffer_manager-0.1.2.dist-info/RECORD
