Metadata-Version: 2.1
Name: steam-tradeoffer-manager
Version: 0.1.2
Summary: Small package that help managing steam trade offers and steam bots
Home-page: https://github.com/somespecialone/python-steam-tradeoffer-manager/
License: MIT
Keywords: steam,offer,trade,steamio
Author: somespecialone
Author-email: tkachenkodmitriy@yahoo.com
Requires-Python: >=3.10,<4.0
Classifier: Framework :: AsyncIO
Classifier: Intended Audience :: Developers
Classifier: License :: OSI Approved :: MIT License
Classifier: Operating System :: OS Independent
Classifier: Programming Language :: Python :: 3
Classifier: Programming Language :: Python :: 3.10
Classifier: Topic :: Software Development :: Libraries
Classifier: Topic :: Software Development :: Libraries :: Python Modules
Classifier: Typing :: Typed
Requires-Dist: steamio (>=0.8.6,<0.9.0)
Project-URL: Documentation, https://somespecialone.github.io/python-steam-tradeoffer-manager/
Project-URL: Repository, https://github.com/somespecialone/python-steam-tradeoffer-manager/
